[{"breeds":[],"id":"HJ5nXpT4Q","url":"https://cdn2.thedogapi.com/images/HJ5nXpT4Q.gif","width":393,"height":408},{"breeds":[],"id":"B1vimaTE7","url":"https://cdn2.thedogapi.com/images/B1vimaTE7.gif","width":196,"height":97},{"breeds":[],"id":"rkq57TpVm","url":"https://cdn2.thedogapi.com/images/rkq57TpVm.gif","width":450,"height":237},{"breeds":[],"id":"SkatQTaEQ","url":"https://cdn2.thedogapi.com/images/SkatQTaEQ.gif","width":450,"height":203},{"breeds":[],"id":"r12d7apV7","url":"https://cdn2.thedogapi.com/images/r12d7apV7.gif","width":495,"height":354},{"breeds":[],"id":"BJUum6T4X","url":"https://cdn2.thedogapi.com/images/BJUum6T4X.gif","width":500,"height":280},{"breeds":[],"id":"Bkov76pEm","url":"https://cdn2.thedogapi.com/images/Bkov76pEm.gif","width":350,"height":263},{"breeds":[],"id":"H1iHQpaVX","url":"https://cdn2.thedogapi.com/images/H1iHQpaVX.gif","width":477,"height":251},{"breeds":[],"id":"H1yHQaaNX","url":"https://cdn2.thedogapi.com/images/H1yHQaaNX.gif","width":350,"height":217},{"breeds":[],"id":"r1VV7pTV7","url":"https://cdn2.thedogapi.com/images/r1VV7pTV7.gif","width":500,"height":281}]