[{"breeds":[],"id":"UgsTQwzPB","url":"https://cdn2.thecatapi.com/images/UgsTQwzPB.jpg","width":3226,"height":2419},{"breeds":[],"id":"xwX5ISvy1","url":"https://cdn2.thecatapi.com/images/xwX5ISvy1.jpg","width":3024,"height":4032},{"breeds":[],"id":"idM7U1tMI","url":"https://cdn2.thecatapi.com/images/idM7U1tMI.png","width":640,"height":640},{"breeds":[],"id":"77-151Rd3","url":"https://cdn2.thecatapi.com/images/77-151Rd3.jpg","width":3456,"height":4608},{"breeds":[],"id":"5dZ97_h1Q","url":"https://cdn2.thecatapi.com/images/5dZ97_h1Q.jpg","width":2536,"height":1512},{"breeds":[],"id":"sd-KewSuc","url":"https://cdn2.thecatapi.com/images/sd-KewSuc.jpg","width":1223,"height":1280},{"breeds":[],"id":"0z9M8VaWU","url":"https://cdn2.thecatapi.com/images/0z9M8VaWU.jpg","width":3780,"height":2592},{"breeds":[],"id":"aa8nfFuof","url":"https://cdn2.thecatapi.com/images/aa8nfFuof.jpg","width":5184,"height":3456},{"breeds":[],"id":"hlDfXy9EC","url":"https://cdn2.thecatapi.com/images/hlDfXy9EC.jpg","width":3456,"height":5184},{"breeds":[],"id":"LrqTeh7FK","url":"https://cdn2.thecatapi.com/images/LrqTeh7FK.jpg","width":700,"height":525}]